{
  "$type": "System.Collections.Generic.List`1[[NodeManager, Assembly-CSharp]], mscorlib",
  "$values": [
    {
      "$type": "NodeArea, Assembly-CSharp",
      "Velocity": 4.0,
      "PhysicalID": "room3",
      "position": {
        "$type": "System.Single[], mscorlib",
        "$values": [
          -13.8006668,
          15.765,
          -20.0667725
        ]
      },
      "State": 0
    },
    {
      "$type": "NodeExit, Assembly-CSharp",
      "PhysicalID": "ID_TEST_1",
      "position": {
        "$type": "System.Single[], mscorlib",
        "$values": [
          -11.3681755,
          15.765,
          -17.1505
        ]
      },
      "State": 0
    },
    {
      "$type": "NodeFireSensor, Assembly-CSharp",
      "PhysicalID": "13000001",
      "position": {
        "$type": "System.Single[], mscorlib",
        "$values": [
          8.231155,
          15.765,
          -10.9998589
        ]
      },
      "State": 2
    },
    {
      "$type": "NodeArea, Assembly-CSharp",
      "Velocity": 4.0,
      "PhysicalID": "ID_TEST_3",
      "position": {
        "$type": "System.Single[], mscorlib",
        "$values": [
          16.79126,
          15.765,
          26.8041267
        ]
      },
      "State": 0
    },
    {
      "$type": "NodeExit, Assembly-CSharp",
      "PhysicalID": "ID_TEST_4",
      "position": {
        "$type": "System.Single[], mscorlib",
        "$values": [
          -26.578167,
          15.765,
          -8.847622
        ]
      },
      "State": 0
    },
    {
      "$type": "NodeDirection, Assembly-CSharp",
      "PhysicalID": "directionSensor",
      "position": {
        "$type": "System.Single[], mscorlib",
        "$values": [
          8.986355,
          15.765,
          27.4392166
        ]
      },
      "State": 0
    }
  ]
}